{
  "$schema": "https://biomejs.dev/schemas/2.3.11/schema.json",
  "extends": ["../../biome.json"],
  "linter": {
    "rules": {
      "a11y": {
        "noSvgWithoutTitle": "off",
        "useButtonType": "off",
        "useAltText": "off",
        "noStaticElementInteractions": "off"
      },
      "performance": {
        "noImgElement": "off"
      },
      "security": {
        "noDangerouslySetInnerHtml": "off"
      },
      "suspicious": {
        "noTemplateCurlyInString": "off"
      },
      "correctness": {
        "noUnusedVariables": "off"
      }
    }
  },
  "files": {
    "includes": ["!.next", "!.source", "!next-env.d.ts"]
  }
}
